podch/__init__.py
podch/__main__.py
podch/board.py
podch/enums.py
podch/game.py
podch-1.0.2.dist-info/LICENSE
podch-1.0.2.dist-info/METADATA
podch-1.0.2.dist-info/WHEEL
podch-1.0.2.dist-info/top_level.txt
podch-1.0.2.dist-info/RECORD
