Metadata-Version: 2.1
Name: podch
Version: 1.0.2
Summary: Abstract board game
Home-page: https://github.com/SashaVonSup/podch
Author: Aleksandr Sup
Author-email: sup@tmat.me
Classifier: Programming Language :: Python :: 3.10
Classifier: License :: Free for non-commercial use
Classifier: Operating System :: OS Independent
Classifier: Topic :: Games/Entertainment :: Board Games
Classifier: Topic :: Software Development :: Libraries :: Python Modules
Requires-Python: >=3.10
License-File: LICENSE
